```log
Classfile /Users/psxjoy/IdeaProjects/java-concurrency/target/classes/com/boot/jdk/SyncUsingWay.class
  Last modified 2024年7月25日; size 769 bytes
  SHA-256 checksum 69e0f9f1790eb18ec3f3aea7a5256d269edf17e35d08059d503cb1664f6401ab
  Compiled from "SyncUsingWay.java"
public class com.boot.jdk.SyncUsingWay
  minor version: 0
  major version: 52
  flags: (0x0021) ACC_PUBLIC, ACC_SUPER
  this_class: #7                          // com/boot/jdk/SyncUsingWay
  super_class: #8                         // java/lang/Object
  interfaces: 0, fields: 0, methods: 4, attributes: 1
Constant pool:
   #1 = Methodref          #8.#25         // java/lang/Object."<init>":()V
   #2 = Fieldref           #26.#27        // java/lang/System.out:Ljava/io/PrintStream;
   #3 = String             #16            // syncMethod
   #4 = Methodref          #28.#29        // java/io/PrintStream.println:(Ljava/lang/String;)V
   #5 = String             #17            // syncStaticMethod
   #6 = String             #18            // method
   #7 = Class              #30            // com/boot/jdk/SyncUsingWay
   #8 = Class              #31            // java/lang/Object
   #9 = Utf8               <init>
  #10 = Utf8               ()V
  #11 = Utf8               Code
  #12 = Utf8               LineNumberTable
  #13 = Utf8               LocalVariableTable
  #14 = Utf8               this
  #15 = Utf8               Lcom/boot/jdk/SyncUsingWay;
  #16 = Utf8               syncMethod
  #17 = Utf8               syncStaticMethod
  #18 = Utf8               method
  #19 = Utf8               StackMapTable
  #20 = Class              #30            // com/boot/jdk/SyncUsingWay
  #21 = Class              #31            // java/lang/Object
  #22 = Class              #32            // java/lang/Throwable
  #23 = Utf8               SourceFile
  #24 = Utf8               SyncUsingWay.java
  #25 = NameAndType        #9:#10         // "<init>":()V
  #26 = Class              #33            // java/lang/System
  #27 = NameAndType        #34:#35        // out:Ljava/io/PrintStream;
  #28 = Class              #36            // java/io/PrintStream
  #29 = NameAndType        #37:#38        // println:(Ljava/lang/String;)V
  #30 = Utf8               com/boot/jdk/SyncUsingWay
  #31 = Utf8               java/lang/Object
  #32 = Utf8               java/lang/Throwable
  #33 = Utf8               java/lang/System
  #34 = Utf8               out
  #35 = Utf8               Ljava/io/PrintStream;
  #36 = Utf8               java/io/PrintStream
  #37 = Utf8               println
  #38 = Utf8               (Ljava/lang/String;)V
{
  public com.boot.jdk.SyncUsingWay();
    descriptor: ()V
    flags: (0x0001) ACC_PUBLIC
    Code:
      stack=1, locals=1, args_size=1
         0: aload_0
         1: invokespecial #1                  // Method java/lang/Object."<init>":()V
         4: return
      LineNumberTable:
        line 3: 0
      LocalVariableTable:
        Start  Length  Slot  Name   Signature
            0       5     0  this   Lcom/boot/jdk/SyncUsingWay;

  public synchronized void syncMethod();
    descriptor: ()V
    flags: (0x0021) ACC_PUBLIC, ACC_SYNCHRONIZED
    Code:
      stack=2, locals=1, args_size=1
         0: getstatic     #2                  // Field java/lang/System.out:Ljava/io/PrintStream;
         3: ldc           #3                  // String syncMethod
         5: invokevirtual #4                  // Method java/io/PrintStream.println:(Ljava/lang/String;)V
         8: return
      LineNumberTable:
        line 6: 0
        line 7: 8
      LocalVariableTable:
        Start  Length  Slot  Name   Signature
            0       9     0  this   Lcom/boot/jdk/SyncUsingWay;

  public static synchronized void syncStaticMethod();
    descriptor: ()V
    flags: (0x0029) ACC_PUBLIC, ACC_STATIC, ACC_SYNCHRONIZED
    Code:
      stack=2, locals=0, args_size=0
         0: getstatic     #2                  // Field java/lang/System.out:Ljava/io/PrintStream;
         3: ldc           #5                  // String syncStaticMethod
         5: invokevirtual #4                  // Method java/io/PrintStream.println:(Ljava/lang/String;)V
         8: return
      LineNumberTable:
        line 12: 0
        line 13: 8

  public void method();
    descriptor: ()V
    flags: (0x0001) ACC_PUBLIC
    Code:
      stack=2, locals=3, args_size=1
         0: aload_0
         1: dup
         2: astore_1
         3: monitorenter  -PSX  进入同步代码块（进入临界范围内，锁的原子内部）
         4: getstatic     #2                  // Field java/lang/System.out:Ljava/io/PrintStream;
         7: ldc           #6                  // String method
         9: invokevirtual #4                  // Method java/io/PrintStream.println:(Ljava/lang/String;)V
        12: aload_1
        13: monitorexit     -PSX 正常退出同步代码块
        14: goto          22
        17: astore_2
        18: aload_1
        19: monitorexit     -PSX  防止任何异常情况下，退出同步代码块。 JVM 仍然可以释放锁
        20: aload_2
        21: athrow
        22: return
      Exception table:      -PSX 配合异常退出 monitorexit
         from    to  target type
             4    14    17   any
            17    20    17   any
      LineNumberTable:
        line 16: 0
        line 17: 4
        line 18: 12
        line 19: 22
      LocalVariableTable:
        Start  Length  Slot  Name   Signature
            0      23     0  this   Lcom/boot/jdk/SyncUsingWay;
      StackMapTable: number_of_entries = 2
        frame_type = 255 /* full_frame */
          offset_delta = 17
          locals = [ class com/boot/jdk/SyncUsingWay, class java/lang/Object ]
          stack = [ class java/lang/Throwable ]
        frame_type = 250 /* chop */
          offset_delta = 4
}
SourceFile: "SyncUsingWay.java"

```